{"numTotalTestSuites":14,"numPassedTestSuites":14,"numFailedTestSuites":0,"numPendingTestSuites":0,"numTotalTests":39,"numPassedTests":39,"numFailedTests":0,"numPendingTests":0,"numTodoTests":0,"snapshot":{"added":0,"failure":false,"filesAdded":0,"filesRemoved":0,"filesRemovedList":[],"filesUnmatched":0,"filesUpdated":0,"matched":0,"total":0,"unchecked":0,"uncheckedKeysByFile":[],"unmatched":0,"updated":0,"didUpdate":false},"startTime":1727467007032,"success":true,"testResults":[{"assertionResults":[{"ancestorTitles":["createScorecard"],"fullName":"createScorecard should create a Scorecard for a GitHub URL","status":"passed","title":"should create a Scorecard for a GitHub URL","duration":3.504699999999957,"failureMessages":[],"meta":{}},{"ancestorTitles":["createScorecard"],"fullName":"createScorecard should create a Scorecard for an npm URL","status":"passed","title":"should create a Scorecard for an npm URL","duration":1.090599999999995,"failureMessages":[],"meta":{}},{"ancestorTitles":["createScorecard"],"fullName":"createScorecard should throw an error for an invalid URL","status":"passed","title":"should throw an error for an invalid URL","duration":2.022699999999986,"failureMessages":[],"meta":{}},{"ancestorTitles":["createScorecard"],"fullName":"createScorecard should handle npm URL with repository URL ending with .git","status":"passed","title":"should handle npm URL with repository URL ending with .git","duration":0.7746000000000777,"failureMessages":[],"meta":{}},{"ancestorTitles":["createScorecard"],"fullName":"createScorecard should handle npm URL when repository URL is not provided","status":"passed","title":"should handle npm URL when repository URL is not provided","duration":0.6480999999999995,"failureMessages":[],"meta":{}}],"startTime":1727467007720,"endTime":1727467007728.6482,"status":"passed","message":"","name":"C:/Users/chloe/repos/school/450-sd/se-phase1/tests/evaluators/createScorecard.test.ts"},{"assertionResults":[{"ancestorTitles":["evaluateModule"],"fullName":"evaluateModule should evaluate all metrics and return results","status":"passed","title":"should evaluate all metrics and return results","duration":8.05099999999993,"failureMessages":[],"meta":{}},{"ancestorTitles":["evaluateModule"],"fullName":"evaluateModule should handle errors from createScorecard","status":"passed","title":"should handle errors from createScorecard","duration":2.1252000000000635,"failureMessages":[],"meta":{}}],"startTime":1727467007909,"endTime":1727467007919.1252,"status":"passed","message":"","name":"C:/Users/chloe/repos/school/450-sd/se-phase1/tests/evaluators/evaluateModule.test.ts"},{"assertionResults":[{"ancestorTitles":["BusFactorMetric"],"fullName":"BusFactorMetric should set bus factor to 0 when top contributor has ≥ 80% contributions","status":"passed","title":"should set bus factor to 0 when top contributor has ≥ 80% contributions","duration":5.048099999999977,"failureMessages":[],"meta":{}},{"ancestorTitles":["BusFactorMetric"],"fullName":"BusFactorMetric should set bus factor to 0.2 when top contributor has ≥ 60% contributions","status":"passed","title":"should set bus factor to 0.2 when top contributor has ≥ 60% contributions","duration":0.6270999999999276,"failureMessages":[],"meta":{}},{"ancestorTitles":["BusFactorMetric"],"fullName":"BusFactorMetric should set bus factor to 0.5 when top contributor has ≥ 40% contributions","status":"passed","title":"should set bus factor to 0.5 when top contributor has ≥ 40% contributions","duration":0.5176999999999907,"failureMessages":[],"meta":{}},{"ancestorTitles":["BusFactorMetric"],"fullName":"BusFactorMetric should set bus factor to 1 when top contributor has < 40% contributions","status":"passed","title":"should set bus factor to 1 when top contributor has < 40% contributions","duration":0.45810000000005857,"failureMessages":[],"meta":{}},{"ancestorTitles":["BusFactorMetric"],"fullName":"BusFactorMetric should handle no contributors and set bus factor to 0","status":"passed","title":"should handle no contributors and set bus factor to 0","duration":1.5932000000000244,"failureMessages":[],"meta":{}},{"ancestorTitles":["BusFactorMetric"],"fullName":"BusFactorMetric should handle errors from GitHub API and set bus factor to 0","status":"passed","title":"should handle errors from GitHub API and set bus factor to 0","duration":0.8817999999999984,"failureMessages":[],"meta":{}},{"ancestorTitles":["BusFactorMetric"],"fullName":"BusFactorMetric should calculate and set busFactor_Latency","status":"passed","title":"should calculate and set busFactor_Latency","duration":114.03689999999995,"failureMessages":[],"meta":{}}],"startTime":1727467007659,"endTime":1727467007782.0369,"status":"passed","message":"","name":"C:/Users/chloe/repos/school/450-sd/se-phase1/tests/metrics/busfactorMetric.test.ts"},{"assertionResults":[{"ancestorTitles":["CorrectnessMetric"],"fullName":"CorrectnessMetric should set correctness score to 0.6 when tests are present and bug score is high","status":"passed","title":"should set correctness score to 0.6 when tests are present and bug score is high","duration":6.066500000000019,"failureMessages":[],"meta":{}},{"ancestorTitles":["CorrectnessMetric"],"fullName":"CorrectnessMetric should set correctness score to 0.5 when tests are absent and bug score is neutral","status":"passed","title":"should set correctness score to 0.5 when tests are absent and bug score is neutral","duration":0.9603000000000748,"failureMessages":[],"meta":{}},{"ancestorTitles":["CorrectnessMetric"],"fullName":"CorrectnessMetric should handle missing package.json and set correctness score based on bugs","status":"passed","title":"should handle missing package.json and set correctness score based on bugs","duration":2.387299999999982,"failureMessages":[],"meta":{}},{"ancestorTitles":["CorrectnessMetric"],"fullName":"CorrectnessMetric should handle errors during test check and assign default score","status":"passed","title":"should handle errors during test check and assign default score","duration":1.7206999999999653,"failureMessages":[],"meta":{}},{"ancestorTitles":["CorrectnessMetric"],"fullName":"CorrectnessMetric should handle errors during bug analysis and assign default score","status":"passed","title":"should handle errors during bug analysis and assign default score","duration":1.3263000000000602,"failureMessages":[],"meta":{}},{"ancestorTitles":["CorrectnessMetric"],"fullName":"CorrectnessMetric should handle total correctness score exceeding 1 by capping it at 1","status":"passed","title":"should handle total correctness score exceeding 1 by capping it at 1","duration":1.2187999999999874,"failureMessages":[],"meta":{}}],"startTime":1727467007659,"endTime":1727467007672.2188,"status":"passed","message":"","name":"C:/Users/chloe/repos/school/450-sd/se-phase1/tests/metrics/correctnessMetric.test.ts"},{"assertionResults":[{"ancestorTitles":["LicenseMetric"],"fullName":"LicenseMetric should set license to 1 if approved license is found in LICENSE file","status":"passed","title":"should set license to 1 if approved license is found in LICENSE file","duration":6.166600000000017,"failureMessages":[],"meta":{}},{"ancestorTitles":["LicenseMetric"],"fullName":"LicenseMetric should set license to 0 if no LICENSE file is found","status":"passed","title":"should set license to 0 if no LICENSE file is found","duration":1.9635999999999285,"failureMessages":[],"meta":{}},{"ancestorTitles":["LicenseMetric"],"fullName":"LicenseMetric should set license to 1 if approved license is found in README file","status":"passed","title":"should set license to 1 if approved license is found in README file","duration":2.0557999999999765,"failureMessages":[],"meta":{}},{"ancestorTitles":["LicenseMetric"],"fullName":"LicenseMetric should set license to 0 if no approved license is found in README file","status":"passed","title":"should set license to 0 if no approved license is found in README file","duration":2.032199999999989,"failureMessages":[],"meta":{}},{"ancestorTitles":["LicenseMetric"],"fullName":"LicenseMetric should handle errors and set license to 0","status":"passed","title":"should handle errors and set license to 0","duration":4.259400000000028,"failureMessages":[],"meta":{}}],"startTime":1727467007818,"endTime":1727467007835.2595,"status":"passed","message":"","name":"C:/Users/chloe/repos/school/450-sd/se-phase1/tests/metrics/licenseMetric.test.ts"},{"assertionResults":[{"ancestorTitles":["MaintainersMetric"],"fullName":"MaintainersMetric should set responsiveMaintainer to 1 when average response time ≤ 72 hours","status":"passed","title":"should set responsiveMaintainer to 1 when average response time ≤ 72 hours","duration":6.622999999999934,"failureMessages":[],"meta":{}},{"ancestorTitles":["MaintainersMetric"],"fullName":"MaintainersMetric should set responsiveMaintainer to 0.7 when average response time ≤ 168 hours","status":"passed","title":"should set responsiveMaintainer to 0.7 when average response time ≤ 168 hours","duration":1.095899999999915,"failureMessages":[],"meta":{}},{"ancestorTitles":["MaintainersMetric"],"fullName":"MaintainersMetric should set responsiveMaintainer to 0.4 when average response time ≤ 336 hours","status":"passed","title":"should set responsiveMaintainer to 0.4 when average response time ≤ 336 hours","duration":0.8383000000000038,"failureMessages":[],"meta":{}},{"ancestorTitles":["MaintainersMetric"],"fullName":"MaintainersMetric should set responsiveMaintainer to 0 when average response time > 336 hours","status":"passed","title":"should set responsiveMaintainer to 0 when average response time > 336 hours","duration":0.8178000000000338,"failureMessages":[],"meta":{}},{"ancestorTitles":["MaintainersMetric"],"fullName":"MaintainersMetric should set responsiveMaintainer to 1 when no issues are found","status":"passed","title":"should set responsiveMaintainer to 1 when no issues are found","duration":0.8116999999999734,"failureMessages":[],"meta":{}},{"ancestorTitles":["MaintainersMetric"],"fullName":"MaintainersMetric should handle errors gracefully and set responsiveMaintainer to 0","status":"passed","title":"should handle errors gracefully and set responsiveMaintainer to 0","duration":1.269900000000007,"failureMessages":[],"meta":{}},{"ancestorTitles":["MaintainersMetric"],"fullName":"MaintainersMetric should handle issues with no maintainer responses","status":"passed","title":"should handle issues with no maintainer responses","duration":0.8919999999999391,"failureMessages":[],"meta":{}},{"ancestorTitles":["MaintainersMetric"],"fullName":"MaintainersMetric should calculate and set responsiveMaintainer_Latency","status":"passed","title":"should calculate and set responsiveMaintainer_Latency","duration":110.81119999999999,"failureMessages":[],"meta":{}}],"startTime":1727467007659,"endTime":1727467007782.8113,"status":"passed","message":"","name":"C:/Users/chloe/repos/school/450-sd/se-phase1/tests/metrics/maintainersMetric.test.ts"},{"assertionResults":[{"ancestorTitles":["RampUpMetric"],"fullName":"RampUpMetric should initialize correctly","status":"passed","title":"should initialize correctly","duration":3.8053999999999633,"failureMessages":[],"meta":{}},{"ancestorTitles":["RampUpMetric"],"fullName":"RampUpMetric should return a score of 0 if the repository has no README","status":"passed","title":"should return a score of 0 if the repository has no README","duration":1.2960000000000491,"failureMessages":[],"meta":{}},{"ancestorTitles":["RampUpMetric"],"fullName":"RampUpMetric should set ramp up score to 1 if README contains all important sections","status":"passed","title":"should set ramp up score to 1 if README contains all important sections","duration":17.21460000000002,"failureMessages":[],"meta":{}},{"ancestorTitles":["RampUpMetric"],"fullName":"RampUpMetric should set ramp up score to 0.2 if README contains more than two code blocks","status":"passed","title":"should set ramp up score to 0.2 if README contains more than two code blocks","duration":3.370800000000031,"failureMessages":[],"meta":{}},{"ancestorTitles":["RampUpMetric"],"fullName":"RampUpMetric should set ramp up score to 0.1 if README contains few linting errors","status":"passed","title":"should set ramp up score to 0.1 if README contains few linting errors","duration":2.7907000000000153,"failureMessages":[],"meta":{}},{"ancestorTitles":["RampUpMetric"],"fullName":"RampUpMetric should set ramp up score to 0.1 if README contains more than 5 links","status":"passed","title":"should set ramp up score to 0.1 if README contains more than 5 links","duration":19.88029999999992,"failureMessages":[],"meta":{}}],"startTime":1727467007759,"endTime":1727467007807.8804,"status":"passed","message":"","name":"C:/Users/chloe/repos/school/450-sd/se-phase1/tests/metrics/rampupMetric.test.ts"}]}